{
   "agent": "websock secure server",
   "behavior": "OK",
   "behaviorClose": "OK",
   "case": 59,
   "closedByMe": false,
   "createStats": true,
   "createWirelog": true,
   "description": "Send text Message fragmented into 2 fragments, then Continuation Frame with FIN = false where there is nothing to continue, then unfragmented Text Message, all sent in one chop.",
   "droppedByMe": false,
   "duration": 1,
   "expectation": "The connection is failed immediately, since there is no message to continue.",
   "expected": {
      "NON-STRICT": [],
      "OK": [
         [
            "message",
            "fragment1fragment2",
            false
         ]
      ]
   },
   "expectedClose": {
      "closeCode": [
         1002
      ],
      "closedByMe": false,
      "requireClean": false
   },
   "failedByMe": false,
   "httpRequest": "GET /wss HTTP/1.1\r\nUser-Agent: AutobahnTestSuite/0.8.2-0.10.9\r\nHost: 127.0.0.1:8889\r\nUpgrade: WebSocket\r\nConnection: Upgrade\r\nPragma: no-cache\r\nCache-Control: no-cache\r\nSec-WebSocket-Key: 73PGn23iiBBMJIF86ANMCA==\r\nSec-WebSocket-Version: 13\r\n\r\n",
   "httpResponse": "HTTP/1.1 101 Switching Protocols\r\nDate: Wed, 04 Aug 2021 16:31:03 GMT\r\nUpgrade: websocket\r\nConnection: Upgrade\r\nSec-Websocket-Accept: jBGemzZ+ZlW4Iqc9E9PBkhkc3eE=\r\n\r\n",
   "id": "5.15",
   "isServer": false,
   "localCloseCode": null,
   "localCloseReason": null,
   "received": [
      [
         "message",
         "fragment1fragment2",
         false
      ]
   ],
   "remoteCloseCode": null,
   "remoteCloseReason": null,
   "reportCompressionRatio": false,
   "reportTime": false,
   "result": "Actual events match at least one expected.",
   "resultClose": "Connection was properly closed",
   "rxFrameStats": {
      "1": 1
   },
   "rxOctetStats": {
      "20": 1,
      "166": 1
   },
   "started": "2021-08-04T16:31:03.364Z",
   "trafficStats": null,
   "txFrameStats": {
      "0": 2,
      "1": 2
   },
   "txOctetStats": {
      "15": 4,
      "243": 1
   },
   "wasClean": false,
   "wasCloseHandshakeTimeout": false,
   "wasNotCleanReason": "peer dropped the TCP connection without previous WebSocket closing handshake",
   "wasOpenHandshakeTimeout": false,
   "wasServerConnectionDropTimeout": false,
   "wirelog": [
      [
         "TO",
         [
            243,
            "474554202f77737320485454502f312e310d0a557365722d4167656e743a204175746f6261686e5465737453756974652f302e382e322d302e31302e390d0a48 ..."
         ],
         false
      ],
      [
         "RO",
         [
            166,
            "485454502f312e312031303120537769746368696e672050726f746f636f6c730d0a446174653a205765642c2030342041756720323032312031363a33313a30 ..."
         ]
      ],
      [
         "TF",
         [
            9,
            "fragment1"
         ],
         1,
         false,
         0,
         "501ca8c5",
         null,
         null,
         false
      ],
      [
         "TO",
         [
            15,
            "0189501ca8c5366ec9a23d79c6b161"
         ],
         false
      ],
      [
         "TF",
         [
            9,
            "fragment2"
         ],
         0,
         true,
         0,
         "0aa85ec8",
         null,
         null,
         false
      ],
      [
         "TO",
         [
            15,
            "80890aa85ec86cda3faf67cd30bc38"
         ],
         false
      ],
      [
         "TF",
         [
            9,
            "fragment3"
         ],
         0,
         false,
         0,
         "14a7b695",
         null,
         null,
         false
      ],
      [
         "TO",
         [
            15,
            "008914a7b69572d5d7f279c2d8e127"
         ],
         false
      ],
      [
         "TF",
         [
            9,
            "fragment4"
         ],
         1,
         true,
         0,
         "2d5a6b96",
         null,
         null,
         false
      ],
      [
         "TO",
         [
            15,
            "81892d5a6b964b280af1403f05e219"
         ],
         false
      ],
      [
         "KL",
         1
      ],
      [
         "RO",
         [
            20,
            "8112667261676d656e7431667261676d656e7432"
         ]
      ],
      [
         "RF",
         [
            18,
            "fragment1fragment2"
         ],
         1,
         true,
         0,
         false,
         null
      ]
   ]
}