{
   "agent": "websock secure server",
   "behavior": "OK",
   "behaviorClose": "OK",
   "case": 73,
   "closedByMe": false,
   "createStats": true,
   "createWirelog": true,
   "description": "Send invalid UTF-8 text message in fragments of 1 octet, resulting in frames ending on positions which are not code point ends.<br><br>MESSAGE:<br>cebae1bdb9cf83cebcceb5eda080656469746564",
   "droppedByMe": false,
   "duration": 1,
   "expectation": "The connection is failed immediately, since the payload is not valid UTF-8.",
   "expected": {
      "OK": []
   },
   "expectedClose": {
      "closeCode": [
         1007
      ],
      "closedByMe": false,
      "closedByWrongEndpointIsFatal": true,
      "requireClean": false
   },
   "failedByMe": false,
   "httpRequest": "GET /wss HTTP/1.1\r\nUser-Agent: AutobahnTestSuite/0.8.2-0.10.9\r\nHost: 127.0.0.1:8889\r\nUpgrade: WebSocket\r\nConnection: Upgrade\r\nPragma: no-cache\r\nCache-Control: no-cache\r\nSec-WebSocket-Key: ShAGc2dpdV5MuOSxUXg8zQ==\r\nSec-WebSocket-Version: 13\r\n\r\n",
   "httpResponse": "HTTP/1.1 101 Switching Protocols\r\nDate: Wed, 04 Aug 2021 16:31:05 GMT\r\nUpgrade: websocket\r\nConnection: Upgrade\r\nSec-Websocket-Accept: DO4QWR9Ky0fH/s/+/ueOcJ2MFiM=\r\n\r\n",
   "id": "6.3.2",
   "isServer": false,
   "localCloseCode": null,
   "localCloseReason": null,
   "received": [],
   "remoteCloseCode": null,
   "remoteCloseReason": null,
   "reportCompressionRatio": false,
   "reportTime": false,
   "result": "Actual events match at least one expected.",
   "resultClose": "Connection was properly closed",
   "rxFrameStats": {},
   "rxOctetStats": {
      "166": 1
   },
   "started": "2021-08-04T16:31:05.557Z",
   "trafficStats": null,
   "txFrameStats": {
      "0": 20,
      "1": 1
   },
   "txOctetStats": {
      "6": 1,
      "7": 20,
      "243": 1
   },
   "wasClean": false,
   "wasCloseHandshakeTimeout": false,
   "wasNotCleanReason": "peer dropped the TCP connection without previous WebSocket closing handshake",
   "wasOpenHandshakeTimeout": false,
   "wasServerConnectionDropTimeout": false,
   "wirelog": [
      [
         "TO",
         [
            243,
            "474554202f77737320485454502f312e310d0a557365722d4167656e743a204175746f6261686e5465737453756974652f302e382e322d302e31302e390d0a48 ..."
         ],
         false
      ],
      [
         "RO",
         [
            166,
            "485454502f312e312031303120537769746368696e672050726f746f636f6c730d0a446174653a205765642c2030342041756720323032312031363a33313a30 ..."
         ]
      ],
      [
         "TF",
         [
            1,
            "0xce"
         ],
         1,
         false,
         0,
         "4d005013",
         null,
         null,
         false
      ],
      [
         "TO",
         [
            7,
            "01814d00501383"
         ],
         false
      ],
      [
         "TF",
         [
            1,
            "0xba"
         ],
         0,
         false,
         0,
         "d197f47b",
         null,
         null,
         false
      ],
      [
         "TO",
         [
            7,
            "0081d197f47b6b"
         ],
         false
      ],
      [
         "TF",
         [
            1,
            "0xe1"
         ],
         0,
         false,
         0,
         "078237a3",
         null,
         null,
         false
      ],
      [
         "TO",
         [
            7,
            "0081078237a3e6"
         ],
         false
      ],
      [
         "TF",
         [
            1,
            "0xbd"
         ],
         0,
         false,
         0,
         "b4e785a6",
         null,
         null,
         false
      ],
      [
         "TO",
         [
            7,
            "0081b4e785a609"
         ],
         false
      ],
      [
         "TF",
         [
            1,
            "0xb9"
         ],
         0,
         false,
         0,
         "04dffd82",
         null,
         null,
         false
      ],
      [
         "TO",
         [
            7,
            "008104dffd82bd"
         ],
         false
      ],
      [
         "TF",
         [
            1,
            "0xcf"
         ],
         0,
         false,
         0,
         "05461894",
         null,
         null,
         false
      ],
      [
         "TO",
         [
            7,
            "008105461894ca"
         ],
         false
      ],
      [
         "TF",
         [
            1,
            "0x83"
         ],
         0,
         false,
         0,
         "39b24001",
         null,
         null,
         false
      ],
      [
         "TO",
         [
            7,
            "008139b24001ba"
         ],
         false
      ],
      [
         "TF",
         [
            1,
            "0xce"
         ],
         0,
         false,
         0,
         "5c72dc7e",
         null,
         null,
         false
      ],
      [
         "TO",
         [
            7,
            "00815c72dc7e92"
         ],
         false
      ],
      [
         "TF",
         [
            1,
            "0xbc"
         ],
         0,
         false,
         0,
         "8fc8b911",
         null,
         null,
         false
      ],
      [
         "TO",
         [
            7,
            "00818fc8b91133"
         ],
         false
      ],
      [
         "TF",
         [
            1,
            "0xce"
         ],
         0,
         false,
         0,
         "95740e9a",
         null,
         null,
         false
      ],
      [
         "TO",
         [
            7,
            "008195740e9a5b"
         ],
         false
      ],
      [
         "TF",
         [
            1,
            "0xb5"
         ],
         0,
         false,
         0,
         "ed3d5502",
         null,
         null,
         false
      ],
      [
         "TO",
         [
            7,
            "0081ed3d550258"
         ],
         false
      ],
      [
         "TF",
         [
            1,
            "0xed"
         ],
         0,
         false,
         0,
         "c42d607a",
         null,
         null,
         false
      ],
      [
         "TO",
         [
            7,
            "0081c42d607a29"
         ],
         false
      ],
      [
         "TF",
         [
            1,
            "0xa0"
         ],
         0,
         false,
         0,
         "3a9853f1",
         null,
         null,
         false
      ],
      [
         "TO",
         [
            7,
            "00813a9853f19a"
         ],
         false
      ],
      [
         "TF",
         [
            1,
            "0x80"
         ],
         0,
         false,
         0,
         "9036f8f7",
         null,
         null,
         false
      ],
      [
         "TO",
         [
            7,
            "00819036f8f710"
         ],
         false
      ],
      [
         "TF",
         [
            1,
            "e"
         ],
         0,
         false,
         0,
         "64d0b13c",
         null,
         null,
         false
      ],
      [
         "TO",
         [
            7,
            "008164d0b13c01"
         ],
         false
      ],
      [
         "TF",
         [
            1,
            "d"
         ],
         0,
         false,
         0,
         "cd4bf435",
         null,
         null,
         false
      ],
      [
         "TO",
         [
            7,
            "0081cd4bf435a9"
         ],
         false
      ],
      [
         "TF",
         [
            1,
            "i"
         ],
         0,
         false,
         0,
         "7e114fdf",
         null,
         null,
         false
      ],
      [
         "TO",
         [
            7,
            "00817e114fdf17"
         ],
         false
      ],
      [
         "TF",
         [
            1,
            "t"
         ],
         0,
         false,
         0,
         "60688b81",
         null,
         null,
         false
      ],
      [
         "TO",
         [
            7,
            "008160688b8114"
         ],
         false
      ],
      [
         "TF",
         [
            1,
            "e"
         ],
         0,
         false,
         0,
         "f34a5c07",
         null,
         null,
         false
      ],
      [
         "TO",
         [
            7,
            "0081f34a5c0796"
         ],
         false
      ],
      [
         "TF",
         [
            1,
            "d"
         ],
         0,
         false,
         0,
         "75f47386",
         null,
         null,
         false
      ],
      [
         "TO",
         [
            7,
            "008175f4738611"
         ],
         false
      ],
      [
         "TF",
         [
            0,
            ""
         ],
         0,
         true,
         0,
         "86c9e498",
         null,
         null,
         false
      ],
      [
         "TO",
         [
            6,
            "808086c9e498"
         ],
         false
      ],
      [
         "KL",
         1
      ]
   ]
}