{
   "agent": "websock secure server",
   "behavior": "OK",
   "behaviorClose": "OK",
   "case": 59,
   "closedByMe": false,
   "createStats": true,
   "createWirelog": true,
   "description": "Send text Message fragmented into 2 fragments, then Continuation Frame with FIN = false where there is nothing to continue, then unfragmented Text Message, all sent in one chop.",
   "droppedByMe": false,
   "duration": 1,
   "expectation": "The connection is failed immediately, since there is no message to continue.",
   "expected": {
      "NON-STRICT": [],
      "OK": [
         [
            "message",
            "fragment1fragment2",
            false
         ]
      ]
   },
   "expectedClose": {
      "closeCode": [
         1002
      ],
      "closedByMe": false,
      "requireClean": false
   },
   "failedByMe": false,
   "httpRequest": "GET /wss HTTP/1.1\r\nUser-Agent: AutobahnTestSuite/0.8.2-0.10.9\r\nHost: 127.0.0.1:8889\r\nUpgrade: WebSocket\r\nConnection: Upgrade\r\nPragma: no-cache\r\nCache-Control: no-cache\r\nSec-WebSocket-Key: HiBglXOFIEU+Z4M5tOlLag==\r\nSec-WebSocket-Version: 13\r\n\r\n",
   "httpResponse": "HTTP/1.1 101 Switching Protocols\r\nDate: Thu, 29 Jul 2021 07:05:11 GMT\r\nUpgrade: websocket\r\nConnection: Upgrade\r\nSec-Websocket-Accept: Q8G/Jxb27o60S9qDJhqCIsQHGs4=\r\n\r\n",
   "id": "5.15",
   "isServer": false,
   "localCloseCode": null,
   "localCloseReason": null,
   "received": [
      [
         "message",
         "fragment1fragment2",
         false
      ]
   ],
   "remoteCloseCode": null,
   "remoteCloseReason": null,
   "reportCompressionRatio": false,
   "reportTime": false,
   "result": "Actual events match at least one expected.",
   "resultClose": "Connection was properly closed",
   "rxFrameStats": {
      "1": 1
   },
   "rxOctetStats": {
      "20": 1,
      "166": 1
   },
   "started": "2021-07-29T07:05:11.379Z",
   "trafficStats": null,
   "txFrameStats": {
      "0": 2,
      "1": 2
   },
   "txOctetStats": {
      "15": 4,
      "243": 1
   },
   "wasClean": false,
   "wasCloseHandshakeTimeout": false,
   "wasNotCleanReason": "peer dropped the TCP connection without previous WebSocket closing handshake",
   "wasOpenHandshakeTimeout": false,
   "wasServerConnectionDropTimeout": false,
   "wirelog": [
      [
         "TO",
         [
            243,
            "474554202f77737320485454502f312e310d0a557365722d4167656e743a204175746f6261686e5465737453756974652f302e382e322d302e31302e390d0a48 ..."
         ],
         false
      ],
      [
         "RO",
         [
            166,
            "485454502f312e312031303120537769746368696e672050726f746f636f6c730d0a446174653a205468752c203239204a756c20323032312030373a30353a31 ..."
         ]
      ],
      [
         "TF",
         [
            9,
            "fragment1"
         ],
         1,
         false,
         0,
         "86174b1c",
         null,
         null,
         false
      ],
      [
         "TO",
         [
            15,
            "018986174b1ce0652a7beb722568b7"
         ],
         false
      ],
      [
         "TF",
         [
            9,
            "fragment2"
         ],
         0,
         true,
         0,
         "33cd3523",
         null,
         null,
         false
      ],
      [
         "TO",
         [
            15,
            "808933cd352355bf54445ea85b5701"
         ],
         false
      ],
      [
         "TF",
         [
            9,
            "fragment3"
         ],
         0,
         false,
         0,
         "0f022b43",
         null,
         null,
         false
      ],
      [
         "TO",
         [
            15,
            "00890f022b4369704a24626745373c"
         ],
         false
      ],
      [
         "TF",
         [
            9,
            "fragment4"
         ],
         1,
         true,
         0,
         "a7b41efb",
         null,
         null,
         false
      ],
      [
         "TO",
         [
            15,
            "8189a7b41efbc1c67f9ccad1708f93"
         ],
         false
      ],
      [
         "KL",
         1
      ],
      [
         "RO",
         [
            20,
            "8112667261676d656e7431667261676d656e7432"
         ]
      ],
      [
         "RF",
         [
            18,
            "fragment1fragment2"
         ],
         1,
         true,
         0,
         false,
         null
      ]
   ]
}